bench/__init__.py
bench/app.py
bench/bench.py
bench/cli.py
bench/exceptions.py
bench/install.py
bench/release.py
bench/commands/__init__.py
bench/commands/config.py
bench/commands/git.py
bench/commands/install.py
bench/commands/make.py
bench/commands/setup.py
bench/commands/update.py
bench/commands/utils.py
bench/config/__init__.py
bench/config/common_site_config.py
bench/config/lets_encrypt.py
bench/config/nginx.py
bench/config/procfile.py
bench/config/production_setup.py
bench/config/redis.py
bench/config/site_config.py
bench/config/supervisor.py
bench/config/systemd.py
bench/config/templates/502.html
bench/config/templates/Procfile
bench/config/templates/bench_manager_nginx.conf
bench/config/templates/frappe_sudoers
bench/config/templates/letsencrypt.cfg
bench/config/templates/nginx.conf
bench/config/templates/nginx_default.conf
bench/config/templates/redis_cache.conf
bench/config/templates/redis_queue.conf
bench/config/templates/supervisor.conf
bench/config/templates/systemd/frappe-bench-frappe-default-worker.service
bench/config/templates/systemd/frappe-bench-frappe-long-worker.service
bench/config/templates/systemd/frappe-bench-frappe-schedule.service
bench/config/templates/systemd/frappe-bench-frappe-short-worker.service
bench/config/templates/systemd/frappe-bench-frappe-web.service
bench/config/templates/systemd/frappe-bench-node-socketio.service
bench/config/templates/systemd/frappe-bench-redis-cache.service
bench/config/templates/systemd/frappe-bench-redis-queue.service
bench/config/templates/systemd/frappe-bench-redis.target
bench/config/templates/systemd/frappe-bench-web.target
bench/config/templates/systemd/frappe-bench-workers.target
bench/config/templates/systemd/frappe-bench.target
bench/patches/__init__.py
bench/patches/patches.txt
bench/patches/v2/__init__.py
bench/patches/v2/fix_backup_cronjob.py
bench/patches/v2/fix_user_permissions.py
bench/patches/v2/set_live_reload_config.py
bench/patches/v2/update_archived_sites.py
bench/playbooks/README.md
dokos_cli-2.9.1.dist-info/METADATA
dokos_cli-2.9.1.dist-info/WHEEL
dokos_cli-2.9.1.dist-info/entry_points.txt
dokos_cli-2.9.1.dist-info/licenses/LICENSE.md
dokos_cli-2.9.1.dist-info/RECORD
