Metadata-Version: 2.1
Name: dokos-cli
Version: 2.9.1
Summary: CLI to manage Multi-tenant deployments for Dodock apps
Project-URL: Changelog, https://github.com/frappe/bench/releases
Project-URL: Documentation, https://frappeframework.com/docs/user/en/bench
Project-URL: Homepage, https://frappe.io/bench
Project-URL: Source, https://github.com/frappe/bench
Author-email: Dokos SAS <hello@dokos.io>
License-Expression: GPL-3.0-only
License-File: LICENSE.md
Classifier: Development Status :: 5 - Production/Stable
Classifier: Environment :: Console
Classifier: License :: OSI Approved :: GNU General Public License v3 (GPLv3)
Classifier: Natural Language :: English
Classifier: Operating System :: MacOS
Classifier: Operating System :: OS Independent
Classifier: Topic :: Software Development :: Build Tools
Classifier: Topic :: Software Development :: User Interfaces
Classifier: Topic :: System :: Installation/Setup
Requires-Python: >=3.10
Requires-Dist: click~=8.1.7
Requires-Dist: gitpython~=3.1.30
Requires-Dist: honcho
Requires-Dist: jinja2~=3.1.3
Requires-Dist: python-crontab~=2.6.0
Requires-Dist: python-gitlab==1.13.0
Requires-Dist: requests
Requires-Dist: semantic-version~=2.8.2
Requires-Dist: setuptools>40.9.0
Requires-Dist: tomli; python_version < '3.11'
